prompt_graph/__init__.py
prompt_graph-1.0.dist-info/LICENSE.txt 
prompt_graph-1.0.dist-info/METADATA
prompt_graph-1.0.dist-info/WHEEL
prompt_graph-1.0.dist-info/top_level.txt
prompt_graph-1.0.dist-info/RECORD
