Metadata-Version: 2.1
Name: prompt_graph
Version: 1.0
Summary: a library built upon PyTorch to easily conduct single or multi-task prompting for pre-trained Graph Neural Networks (GNNs).
Home-page: https://github.com/sheldonresearch/ProG
Author: Chenyi Zi
Author-email: barristan666@gmai.com
License: MIT
Requires-Python: >=3.9
License-File: LICENSE.txt 
